LICENSE.txt
MANIFEST.in
README.rst
setup.py
django_cropper_image/__init__.py
django_cropper_image/config.py
django_cropper_image/fields.py
django_cropper_image/widgets.py
django_cropper_image.egg-info/PKG-INFO
django_cropper_image.egg-info/SOURCES.txt
django_cropper_image.egg-info/dependency_links.txt
django_cropper_image.egg-info/top_level.txt
django_cropper_image/static/django_cropper_image/css/cropper.min.css
django_cropper_image/static/django_cropper_image/css/image_cropper.css
django_cropper_image/static/django_cropper_image/js/cropper.min.js
django_cropper_image/static/django_cropper_image/js/image_cropper.js
django_cropper_image/static/django_cropper_image/js/image_cropper.min.js
django_cropper_image/templates/django_cropper_image/image_cropper_attrs.html
django_cropper_image/templates/django_cropper_image/image_cropper_container.html
django_cropper_image/templates/django_cropper_image/image_cropper_input.html